bendev_tools/__init__.py
bendev_tools-1.0.2.dist-info/licenses/LICENSE
bendev_tools-1.0.2.dist-info/METADATA
bendev_tools-1.0.2.dist-info/WHEEL
bendev_tools-1.0.2.dist-info/top_level.txt
bendev_tools-1.0.2.dist-info/RECORD
